phpIPAM_Scraper-1.1.2.dist-info/DESCRIPTION.rst
phpIPAM_Scraper-1.1.2.dist-info/METADATA
phpIPAM_Scraper-1.1.2.dist-info/RECORD
phpIPAM_Scraper-1.1.2.dist-info/WHEEL
phpIPAM_Scraper-1.1.2.dist-info/entry_points.txt
phpIPAM_Scraper-1.1.2.dist-info/metadata.json
phpIPAM_Scraper-1.1.2.dist-info/top_level.txt
phpipam_scraper/__init__.py
phpipam_scraper/__main__.py
phpipam_scraper/config.py
phpipam_scraper/phpipam.py
